MANIFEST.in
setup.py
Products/__init__.py
Products.SilvaForum.egg-info/PKG-INFO
Products.SilvaForum.egg-info/SOURCES.txt
Products.SilvaForum.egg-info/dependency_links.txt
Products.SilvaForum.egg-info/namespace_packages.txt
Products.SilvaForum.egg-info/not-zip-safe
Products.SilvaForum.egg-info/requires.txt
Products.SilvaForum.egg-info/top_level.txt
Products/SilvaForum/HISTORY.txt
Products/SilvaForum/LICENSE.txt
Products/SilvaForum/LICENSE_JFORUM.txt
Products/SilvaForum/README.txt
Products/SilvaForum/TODO.txt
Products/SilvaForum/__init__.py
Products/SilvaForum/configure.zcml
Products/SilvaForum/content.py
Products/SilvaForum/dtformat.py
Products/SilvaForum/emoticons.py
Products/SilvaForum/ftesting.zcml
Products/SilvaForum/interfaces.py
Products/SilvaForum/testing.py
Products/SilvaForum/views.py
Products/SilvaForum/i18n/__init__.py
Products/SilvaForum/i18n/silvaforum.pot
Products/SilvaForum/i18n/de/LC_MESSAGES/silvaforum.mo
Products/SilvaForum/i18n/de/LC_MESSAGES/silvaforum.po
Products/SilvaForum/i18n/en/LC_MESSAGES/silvaforum.mo
Products/SilvaForum/i18n/en/LC_MESSAGES/silvaforum.po
Products/SilvaForum/i18n/nl/LC_MESSAGES/silvaforum.mo
Products/SilvaForum/i18n/nl/LC_MESSAGES/silvaforum.po
Products/SilvaForum/layout/forum_event_template.pt
Products/SilvaForum/schema/silvaforum-forum.xml
Products/SilvaForum/schema/silvaforum-item.xml
Products/SilvaForum/static/close_window.png
Products/SilvaForum/static/forum.css
Products/SilvaForum/static/forum.js
Products/SilvaForum/static/emoticons/angry.gif
Products/SilvaForum/static/emoticons/apprehension.gif
Products/SilvaForum/static/emoticons/arrow.gif
Products/SilvaForum/static/emoticons/confusion.gif
Products/SilvaForum/static/emoticons/cool.gif
Products/SilvaForum/static/emoticons/embarrassment.gif
Products/SilvaForum/static/emoticons/embarrassment2.gif
Products/SilvaForum/static/emoticons/exclamation.gif
Products/SilvaForum/static/emoticons/happy.gif
Products/SilvaForum/static/emoticons/idea.gif
Products/SilvaForum/static/emoticons/mad.gif
Products/SilvaForum/static/emoticons/question.gif
Products/SilvaForum/static/emoticons/sad.gif
Products/SilvaForum/static/emoticons/shocked.gif
Products/SilvaForum/static/emoticons/surprised.gif
Products/SilvaForum/static/emoticons/twisted.gif
