Metadata-Version: 1.1
Name: Products.SilvaForum
Version: 3.0.3
Summary: Forum content types for Silva CMS
Home-page: https://github.com/silvacms/Products.SilvaForum
Author: Infrae
Author-email: info@infrae.com
License: BSD
Keywords: forum silva zope2
Platform: UNKNOWN
Classifier: Framework :: Zope2
Classifier: License :: OSI Approved :: BSD License
Classifier: Programming Language :: Python
Classifier: Topic :: Software Development :: Libraries :: Python Modules
